LICENSE.txt
MANIFEST.in
README.md
pyproject.toml
setup.py
./fcos/core/csrc/ROIAlign.h
./fcos/core/csrc/ROIPool.h
./fcos/core/csrc/SigmoidFocalLoss.h
./fcos/core/csrc/deform_conv.h
./fcos/core/csrc/deform_pool.h
./fcos/core/csrc/ml_nms.h
./fcos/core/csrc/nms.h
./fcos/core/csrc/cpu/vision.h
./fcos/core/csrc/cuda/vision.h
fcos/__init__.py
fcos/__main__.py
fcos/evaluator.py
fcos/fcos.py
fcos/helpers.py
fcos/trainer.py
fcos.egg-info/PKG-INFO
fcos.egg-info/SOURCES.txt
fcos.egg-info/dependency_links.txt
fcos.egg-info/entry_points.txt
fcos.egg-info/requires.txt
fcos.egg-info/top_level.txt
fcos/configs/FCOS_imprv_R_101_FPN_2x.yaml
fcos/configs/FCOS_imprv_R_50_FPN_1x.yaml
fcos/configs/FCOS_imprv_dcnv2_R_101_FPN_2x.yaml
fcos/configs/FCOS_imprv_dcnv2_R_50_FPN_1x.yaml
fcos/core/__init__.py
fcos/core/config/__init__.py
fcos/core/config/defaults.py
fcos/core/config/paths_catalog.py
fcos/core/csrc/vision.cpp
fcos/core/csrc/cpu/ROIAlign_cpu.cpp
fcos/core/csrc/cpu/nms_cpu.cpp
fcos/core/csrc/cuda/ROIAlign_cuda.cu
fcos/core/csrc/cuda/ROIPool_cuda.cu
fcos/core/csrc/cuda/SigmoidFocalLoss_cuda.cu
fcos/core/csrc/cuda/deform_conv_cuda.cu
fcos/core/csrc/cuda/deform_conv_kernel_cuda.cu
fcos/core/csrc/cuda/deform_pool_cuda.cu
fcos/core/csrc/cuda/deform_pool_kernel_cuda.cu
fcos/core/csrc/cuda/ml_nms.cu
fcos/core/csrc/cuda/nms.cu
fcos/core/data/__init__.py
fcos/core/data/build.py
fcos/core/data/collate_batch.py
fcos/core/data/datasets/__init__.py
fcos/core/data/datasets/coco.py
fcos/core/data/datasets/concat_dataset.py
fcos/core/data/datasets/list_dataset.py
fcos/core/data/datasets/voc.py
fcos/core/data/datasets/evaluation/__init__.py
fcos/core/data/datasets/evaluation/coco/__init__.py
fcos/core/data/datasets/evaluation/coco/coco_eval.py
fcos/core/data/datasets/evaluation/voc/__init__.py
fcos/core/data/datasets/evaluation/voc/voc_eval.py
fcos/core/data/samplers/__init__.py
fcos/core/data/samplers/distributed.py
fcos/core/data/samplers/grouped_batch_sampler.py
fcos/core/data/samplers/iteration_based_batch_sampler.py
fcos/core/data/transforms/__init__.py
fcos/core/data/transforms/build.py
fcos/core/data/transforms/transforms.py
fcos/core/engine/__init__.py
