Metadata-Version: 2.1
Name: fcos
Version: 0.9.8
Summary: Fully convolutional one-stage object detection (FCOS)
Home-page: https://github.com/best-of-acrv/fcos
Author: Ben Talbot
Author-email: b.talbot@qut.edu.au
License: UNKNOWN
Platform: UNKNOWN
Classifier: Development Status :: 4 - Beta
Classifier: Programming Language :: Python :: 3
Classifier: License :: OSI Approved :: BSD License
Classifier: Operating System :: OS Independent
License-File: LICENSE.txt
